wh2api/__init__.py
wh2api/wh.py
wh2api/lib/__init__.py
wh2api/lib/api_list.py
wh2api/lib/asset.py
wh2api/lib/asset_task.py
wh2api/lib/category.py
wh2api/lib/episode.py
wh2api/lib/mytask.py
wh2api/lib/org.py
wh2api/lib/project.py
wh2api/lib/publish.py
wh2api/lib/sequence.py
wh2api/lib/shot.py
wh2api/lib/shot_task.py
wh2api/lib/team.py
wh2api/lib/track.py
wh2api/lib/user.py
wh2api/lib/version.py
wh2api/lib/wh_setting.py
wh2api2-1.0.2.dist-info/METADATA
wh2api2-1.0.2.dist-info/WHEEL
wh2api2-1.0.2.dist-info/top_level.txt
wh2api2-1.0.2.dist-info/RECORD
