Metadata-Version: 2.1
Name: wh2api2
Version: 1.0.2
Summary: wormhole API for Python
Home-page: http://wormholepipeline.com
Author: C2monster
Author-email: contact@c2monster.com
License: UNKNOWN
Keywords: wormhole,sdk,wh_api
Platform: UNKNOWN
Classifier: Programming Language :: Python :: 2
Classifier: Programming Language :: Python :: 2.7
Requires-Python: >=2
